torchfsm/__init__.py
torchfsm/_type.py
torchfsm/_utils.py
torchfsm/errors.py
torchfsm/functional.py
torchfsm/mesh.py
torchfsm/pde.py
torchfsm/traj_recorder.py
torchfsm/field/__init__.py
torchfsm/field/_diffused_noise.py
torchfsm/field/_energy_spectrum.py
torchfsm/field/_functional_fourier.py
torchfsm/field/_gaussian_blobs.py
torchfsm/field/_kolm_force.py
torchfsm/field/_normalize.py
torchfsm/field/_truncated_fourier.py
torchfsm/field/_wave_1d.py
torchfsm/integrator/__init__.py
torchfsm/integrator/_etdrk.py
torchfsm/integrator/_rk.py
torchfsm/integrator/_stable_etdrk/__init__.py
torchfsm/integrator/_stable_etdrk/_cached.py
torchfsm/integrator/_stable_etdrk/_setdrk_step.py
torchfsm/integrator/_stable_etdrk/_uncached.py
torchfsm/operator/__init__.py
torchfsm/operator/_base.py
torchfsm/operator/dedicated/__init__.py
torchfsm/operator/dedicated/_gray_scott.py
torchfsm/operator/dedicated/_ks_convection.py
torchfsm/operator/dedicated/_navier_stokes/__init__.py
torchfsm/operator/dedicated/_navier_stokes/_leray.py
torchfsm/operator/dedicated/_navier_stokes/_ns_pressure_convection.py
torchfsm/operator/dedicated/_navier_stokes/_value_transformation.py
torchfsm/operator/dedicated/_navier_stokes/_vorticity_convection.py
torchfsm/operator/generic/__init__.py
torchfsm/operator/generic/_advection.py
torchfsm/operator/generic/_biharmonic.py
torchfsm/operator/generic/_conservative_convection.py
torchfsm/operator/generic/_convection.py
torchfsm/operator/generic/_curl.py
torchfsm/operator/generic/_dispersion.py
torchfsm/operator/generic/_div.py
torchfsm/operator/generic/_grad.py
torchfsm/operator/generic/_hyper_diffusion.py
torchfsm/operator/generic/_laplacian.py
torchfsm/operator/generic/_linear_advection.py
torchfsm/operator/generic/_source.py
torchfsm/operator/generic/_spatial_derivative.py
torchfsm/plot/__init__.py
torchfsm/plot/render.py
torchfsm/plot/tools.py
torchfsm/plot/app/__init__.py
torchfsm/plot/app/frame.py
torchfsm/plot/app/frame_slice.py
torchfsm/plot/app/slice.py
torchfsm-0.0.6.dist-info/licenses/LICENSE
torchfsm-0.0.6.dist-info/METADATA
torchfsm-0.0.6.dist-info/WHEEL
torchfsm-0.0.6.dist-info/top_level.txt
torchfsm-0.0.6.dist-info/RECORD
