Metadata-Version: 2.4
Name: torchfsm
Version: 0.0.6
Summary: Fourier Spectral Method with PyTorch
Home-page: https://qiauil.github.io/torchfsm
Author: Qiang Liu, Felix Koehler, Nils Thuerey
Author-email: qiangliu.7@outlook.com
Classifier: Programming Language :: Python :: 3
Classifier: License :: OSI Approved :: MIT License
Classifier: Operating System :: OS Independent
License-File: LICENSE
Requires-Dist: ipython
Requires-Dist: matplotlib
Requires-Dist: numpy
Requires-Dist: torch
Requires-Dist: tqdm
Requires-Dist: vape4d
Dynamic: author
Dynamic: author-email
Dynamic: classifier
Dynamic: description
Dynamic: description-content-type
Dynamic: home-page
Dynamic: license-file
Dynamic: requires-dist
Dynamic: summary
